minimally_sufficient_pandas/__init__.py
minimally_sufficient_pandas/_pandas_accessor.py
minimally_sufficient_pandas-0.0.2.dist-info/LICENSE
minimally_sufficient_pandas-0.0.2.dist-info/METADATA
minimally_sufficient_pandas-0.0.2.dist-info/WHEEL
minimally_sufficient_pandas-0.0.2.dist-info/top_level.txt
minimally_sufficient_pandas-0.0.2.dist-info/RECORD
