Metadata-Version: 2.1
Name: minimally-sufficient-pandas
Version: 0.0.2
Summary: A pandas DataFrame accessor limiting methods to a minimally sufficient subset
Home-page: https://github.com/dexplo/minimally_sufficient_pandas
Author: Ted Petrou
Author-email: petrou.theodore@gmail.com
License: BSD
Keywords: pandas DataFrame minimally sufficient
Platform: UNKNOWN
Classifier: Programming Language :: Python :: 3
Classifier: License :: OSI Approved :: BSD License
Classifier: Operating System :: OS Independent
Requires-Python: >=3.6
Requires-Dist: pandas (>=0.24)
